{"stats":{"minecraft:mined":{"minecraft:dead_bush":3,"minecraft:obsidian":1,"minecraft:dirt":31},"minecraft:used":{"minecraft:redstone":8,"minecraft:oak_button":2,"minecraft:diamond_pickaxe":1,"minecraft:dirt":28,"minecraft:command_block":1,"minecraft:obsidian":16},"minecraft:custom":{"minecraft:jump":73,"minecraft:time_since_rest":417,"minecraft:crouch_one_cm":143,"minecraft:play_one_minute":12603,"minecraft:leave_game":4,"minecraft:sprint_one_cm":8566,"minecraft:time_since_death":12603,"minecraft:walk_on_water_one_cm":36,"minecraft:walk_one_cm":21122,"minecraft:sneak_time":1,"minecraft:fly_one_cm":1058}},"DataVersion":2230}